{
  "persons": [
    {
      "name": "Arto Hellas",
      "number": "040-123456",
      "id": 1
    },
    {
      "name": "Ada Lovelace",
      "number": "39-44-5323523",
      "id": 2
    },
    {
      "name": "Dan Abramov",
      "number": "12-43-234345",
      "id": 3
    },
    {
      "name": "Mary Poppendieck",
      "number": "39-23-6423122",
      "id": 4
    },
    {
      "name": "Daniel",
      "number": "04025648854",
      "id": 5
    },
    {
      "name": "Arti Hellas",
      "number": "5555",
      "id": 6
    },
    {
      "name": "daniele",
      "number": "6666666",
      "id": 9
    },
    {
      "name": "giulia",
      "number": "35",
      "id": 10
    },
    {
      "name": "davidone",
      "number": "21123",
      "id": 12
    },
    {
      "name": "kir",
      "number": "ewfwe",
      "id": 13
    },
    {
      "name": "wefwe ewfwefew",
      "number": "432",
      "id": 14
    },
    {
      "name": "rgeswrgesw",
      "number": "5684564",
      "id": 15
    },
    {
      "name": "o88uo",
      "number": "        8978      ",
      "id": 16
    },
    {
      "name": "elena",
      "number": "111",
      "id": 17
    }
  ]
}